zyfra_check/__init__.py
zyfra_check/check_methods.py
zyfra_check/plugin.py
zyfra_check-0.0.9.dist-info/METADATA
zyfra_check-0.0.9.dist-info/WHEEL
zyfra_check-0.0.9.dist-info/entry_points.txt
zyfra_check-0.0.9.dist-info/top_level.txt
zyfra_check-0.0.9.dist-info/RECORD
