Metadata-Version: 2.1
Name: zyfra-check
Version: 0.0.9
Summary: A plugin that allows multiple failures per test.
Requires-Dist: pytest (>=3.1.1)
Requires-Dist: jira (>=3.4.1)
Requires-Dist: testit-adapter-pytest (>=1.1.2)
